elsevier_latex_preparation/__init__.py
elsevier_latex_preparation/latex_coversion_code.py
elsevier_latex_preparation/thinker_interface.py
elsevier_latex_preparation-0.2.1.dist-info/METADATA
elsevier_latex_preparation-0.2.1.dist-info/WHEEL
elsevier_latex_preparation-0.2.1.dist-info/entry_points.txt
elsevier_latex_preparation-0.2.1.dist-info/top_level.txt
elsevier_latex_preparation-0.2.1.dist-info/RECORD
