Metadata-Version: 2.4
Name: elsevier-latex-preparation
Version: 0.2.1
Summary: Merge LaTeX files and resources for Elsevier Editorial Manager submission
Author-email: Pietro Ungar <pietro.ungar@unifi.it>
License: MIT
Project-URL: Homepage, https://github.com/SERGGroup/ElsevierLatexPreparation
Project-URL: Repository, https://github.com/SERGGroup/ElsevierLatexPreparation
Project-URL: Bug Tracker, https://github.com/SERGGroup/ElsevierLatexPreparation/issues
Classifier: Programming Language :: Python :: 3
Classifier: License :: OSI Approved :: MIT License
Classifier: Operating System :: OS Independent
Requires-Python: >=3.7
Requires-Dist: ttkthemes
